notion_renderer/__init__.py
notion_renderer/__main__.py
notion_renderer/example.py
notion_renderer/notion/__init__.py
notion_renderer/notion/block.py
notion_renderer/notion/client.py
notion_renderer/notion/collection.py
notion_renderer/notion/logger.py
notion_renderer/notion/maps.py
notion_renderer/notion/markdown.py
notion_renderer/notion/monitor.py
notion_renderer/notion/operations.py
notion_renderer/notion/records.py
notion_renderer/notion/settings.py
notion_renderer/notion/smoke_test.py
notion_renderer/notion/space.py
notion_renderer/notion/store.py
notion_renderer/notion/user.py
notion_renderer/notion/utils.py
notion_renderer/py.typed
notion_renderer/renderer.py
notion_renderer-0.2.18.dist-info/entry_points.txt
notion_renderer-0.2.18.dist-info/LICENSE
notion_renderer-0.2.18.dist-info/WHEEL
notion_renderer-0.2.18.dist-info/METADATA
notion_renderer-0.2.18.dist-info/RECORD
